Vivado/i2c_controller_mcp4725/i2c_controller_mcp4725.srcs/sources_1/new/i2c_controller_mcp4725.v
`timescale 1ns / 1ps
//////////////////////////////////////////////////////////////////////////////////
// Create Date: 01/11/2025 01:42:21 PM
// Design Name: I2C Controller for MCP4725 DAC
// Module Name: i2c_controller_mcp4725
// Project Name: 
// Target Devices: 
// Tool Versions: 
// Description: I2C Controller for MCP4725 DAC. Initial design focuses on Standar Mode (100kHz)
// which is the default mode for the MCP4725.
// The design shall later be extended to fast mode (400kHz).I am using a board from Aliexpress that 
// used 4.7K pullups. They need to be replaced to <1K for in case the design has to be adapted for high-speed mode (3.4MHz).
// We shall use two shift registers, one for address and one for data. The address is 4-bits and the data is 12-bits with MCP4725.
// We shall use 8bit reg for address which also holds 1-bit for always write (0).
// We shall use a 16-bit reg for data.with the LSB bits 0-3 being always 0.    
// We shall use the device in Normal Mode and not Power Down Mode yet.
// We shall also not write to EEPROm yet.
// FSM is placed FPAG clock (aka system clock). The I2C clock is dericed from the FPGA clock. We used sclk to take care of state transitions.
// This was we can overcome issues related to edge senssitivity if FSM had to be placed under sclk.
//////////////////////////////////////////////////////////////////////////////////


module i2c_controller_mcp4725(
    input clk,					// FPGA clock
    input reset,				// Reset line
    //input  [15:0] data,		    // 16-bit data byte
    output reg scl,             // I2C clock line
    inout wire sda,              // I2C data line
    output reg done,             // Done signal to indicate end of transaction
    output reg nACK,             // NACK signal to indicate no ack from the device
    output reg bus_busy                   // signal to report bus busy
    );

    reg [7:0] shift_reg_addr;	    // (7-bit address + 1-bit R/~W) byte
    reg [7:0] shift_reg_msb_data;	// msb byte
    reg [7:0] shift_reg_lsb_data;   // lsb byte (4-bits data + 4-bits don't care)
    reg [7:0] shift_reg_cmd;	    // shift reg for cmd byte
    reg [15:0] clk_div_counter;     // 100MHz FPGA clock to 100KHz I2C clock
    reg [7:0] bus_idle_counter;      // 100KHz I2C scl to 1ms bus idle time
    reg [3:0] bitcount_addr;        // variable to track the number of bits for address shift register
    reg [3:0] bitcount_cmd;         // variable to track the number of bits for cmd shift register  
    reg [3:0] bitcount_msb_data;    // variable to track the number of bits in MSB for data shift register
    reg [3:0] bitcount_lsb_data;    // variable to track the number of bits in LSB for data shift register
    reg [3:0] state_reg;            // next state register for the FMS
    reg sda_out;                    // internal signal to drive sda
    reg sda_dir;                    // internal signal to control sda direction
        
    //System parameters
    //Fixed device address for the MCP4725
    parameter MCP4725 = 7'h60;  //MCP7425 device address
    //Command byte for Standard Mode wihtout EEPROM write
    //||C2|C1|C0|X|X|PD1|PD0|X||D11|D10|D9|D8|D7|D6|D5|D4||D3|D2|D1|D0|X|X|X|X||
    parameter CMDBYTE = 8'h59;  
    //For testing purposes input data is handled as parameter- 0xABC.
    //This shall be replaced with an input port in the final design.
    parameter LSBBYTE = 8'hBC;  //LSB data byte
    parameter MSBBYTE = 8'h0A;  //MSB data byte
    parameter CLKDIV = 16'd500; //100MHz FPGA clock to 100KHz I2C clock
    parameter SCL_SETUP_DLY = 8'd100;   //100 * 100ns = 10us. This is a critical parameter can be adpated as per datatsheet.
    // FSM state transitions happen when scl is low and this setup time has been elapsed.
    //I have chosen 1/5th of the scl pulse, so that by the time scl goes high, the FSM state transitions occur and signals get stabilized.

    //State machine states parameters
    parameter idle_state = 4'd0;
    parameter bus_idle_state = 4'd1;
    parameter start_state = 4'd2; 
    parameter send_addr_state = 4'd3;
    parameter wait_ack_addr_state = 4'd4;
    parameter send_cmd_state = 4'd5;
    parameter wait_cmd_ack_state = 4'd6;
    parameter send_data_msb_state = 4'd7;
    parameter wait_data_msb_ack_state = 4'd8;
    parameter send_data_lsb_state = 4'd9;
    parameter wait_data_lsb_ack_state = 4'd10;
    parameter stop_state = 4'd11;

    //SCLK generation from FPGA clock
    always @(posedge clk, posedge reset) begin
        if(reset) begin
            sda_out <= 1'b1;
            sda_dir <= 1'b0;    //means sda is high impedance
            scl <= 1'b1;        //scl is high on reset
            clk_div_counter <= 16'd0;
        end
        else begin
            if(clk_div_counter >= CLKDIV) begin
                    scl <= ~scl;
                    clk_div_counter <= 16'd0;
            end
            else clk_div_counter <= clk_div_counter + 16'd1;
        end
    end
    
    //SDA control is placed under the FPGA clock
    always @(negedge clk, posedge reset) begin
        if(reset) state_reg <= idle_state;
        else begin
            case(state_reg)
                idle_state: begin 
                    sda_dir <= 1'b0;    //sda line is high impedance
                    sda_out <= 1'bz;
                end
                bus_idle_state: begin
                    sda_dir <= 1'b0;    //sda line is high impedance
                    sda_out <= 1'bz;
                end
                start_state: begin
                    if(scl == 1'b1) begin   //start condition
                        sda_dir <= 1'b1;    //sda line is driven by master
                        sda_out <= 1'b0;
                    end
                    else begin
                        sda_dir <= 1'b0;    //sda line is high impedance
                        sda_out <= 1'bz;
                    end
                end
                send_addr_state: begin
                    sda_dir <= 1'b1;    //sda line is driven by master
                    sda_out <= shift_reg_addr[7];
                end
                wait_ack_addr_state: begin
                    sda_dir <= 1'b0;    //sda line is high impedance
                    sda_out <= 1'bz;
                end
                send_cmd_state: begin
                    sda_dir <= 1'b1;    //sda line is driven by master
                    sda_out <= shift_reg_cmd[7];
                end
                wait_cmd_ack_state: begin
                    sda_dir <= 1'b0;    //sda line is high impedance
                    sda_out <= 1'bz;
                end
                send_data_msb_state: begin
                    sda_dir <= 1'b1;    //sda line is driven by master
                    sda_out <= shift_reg_msb_data[7];
                end
                wait_data_msb_ack_state: begin
                    sda_dir <= 1'b0;    //sda line is high impedance
                    sda_out <= 1'bz;
                end
                send_data_lsb_state: begin
                    sda_dir <= 1'b1;    //sda line is driven by master
                    sda_out <= shift_reg_lsb_data[7];
                end
                wait_data_lsb_ack_state: begin
                    sda_dir <= 1'b0;    //sda line is high impedance
                    sda_out <= 1'bz;
                end
                stop_state: begin
                    if(scl == 1'b1) begin   //stop condition
                        sda_dir <= 1'b1;    //sda line is driven by master
                        sda_out <= 1'b1;
                    end
                    else begin
                    sda_dir <= 1'b0;    //sda line is high impedance
                    sda_out <= 1'bz;
                end
                end
                default: begin
                    sda_dir <= 1'b0;    //sda line is high impedance
                    sda_out <= 1'b1;
                end
            endcase
        end
    end

    // FSM I2C Controller for MCP4725 DAC
    always @(posedge clk, posedge reset) begin
        if (reset) begin
            state_reg <= idle_state;
        end
        else if ((clk_div_counter == SCL_SETUP_DLY) && (scl == 1'b1)) begin  // Allow state transition only when scl is low and setup times have met
            case (state_reg)
                idle_state: begin
                    bus_idle_counter <= 8'd0;
                    bitcount_addr <= 4'd0;
                    shift_reg_addr <= {MCP4725, 1'b0};          //Initialize shift_reg_add with the device address
                    shift_reg_cmd <= CMDBYTE;                   //Initialize shift_reg_cmd with the command byte
                    shift_reg_lsb_data <= LSBBYTE;              //Initialize shift_reg_lsb_data with the lsb data byte
                    shift_reg_msb_data <= MSBBYTE;              //Initialize shift_reg_msb_data with the msb data byte
                    nACK <= 1'b0;
                    done <= 1'b0;
                    scl <= 1'b1;    //scl is high on reset
                    bus_busy <= 1'b0;
                    state_reg <= bus_idle_state;
                end
                bus_idle_state: begin
                    if (bus_idle_counter == 8'd5) begin
                        bus_idle_counter <= 8'd0;
                        state_reg <= start_state;
                    end
                    else
                        bus_idle_counter <= bus_idle_counter + 8'd1;
                end
                start_state: begin
                    if(scl == 1'b1) begin
                        nACK <= 1'b0;   // Clear NACK
                        done <= 1'b0;   // Clear done
                        bus_busy <= 1'b1;
                        state_reg <= send_addr_state;
                    end
                    else begin
                        state_reg <= start_state;
                    end
                end
                send_addr_state: begin
                    if(bitcount_addr == 4'd8) begin
                        bitcount_addr <= 4'd0;
                        state_reg <= wait_ack_addr_state;
                    end
                    else begin
                        shift_reg_addr <= {shift_reg_addr[6:0], 1'b0};
                        bitcount_addr <= bitcount_addr + 4'd1;
                        state_reg <= send_addr_state;
                    end
                end
                wait_ack_addr_state: begin
                    if(sda == 1'b0) begin
                        state_reg <= send_cmd_state;
                    end
                    else begin
                        nACK <= 1'b1;   //no ack from the device
                        state_reg <= stop_state;    //we transit to stop state when there is not addr ack from the device.
                    end
                end
                send_cmd_state: begin
                    if(bitcount_cmd == 4'd8) begin
                        bitcount_cmd <= 4'd0;
                        state_reg <= wait_cmd_ack_state;
                    end
                    else begin
                        shift_reg_cmd <= {shift_reg_cmd[6:0], 1'b0};
                        bitcount_cmd <= bitcount_cmd + 4'd1;
                        state_reg <= send_cmd_state;
                    end
                end
                wait_cmd_ack_state: begin
                    if(sda == 1'b0) begin
                        state_reg <= send_data_msb_state;
                    end
                    else begin
                        nACK <= 1'b1;   //no ack from the device
                        state_reg <= stop_state;    //we transit to stop state when there is not cmd ack from the device.
                    end
                end
                send_data_msb_state: begin
                    if(bitcount_msb_data == 4'd8) begin
                        bitcount_msb_data <= 4'd0;
                        state_reg <= wait_data_msb_ack_state;
                    end
                    else begin
                        shift_reg_msb_data <= {shift_reg_msb_data[6:0], 1'b0};  //Note that only the lsb niblle shall be written to the device as the device only supports 12-bit DAC register.
                        bitcount_msb_data <= bitcount_msb_data + 4'd1;
                        state_reg <= send_data_msb_state;
                    end
                end
                wait_data_msb_ack_state: begin
                    if(sda == 1'b0) begin
                        state_reg <= send_data_lsb_state;
                    end
                    else begin
                        nACK <= 1'b1;   //no ack from the device
                        state_reg <= stop_state;    //we transit to stop state when there is not msb data ack from the device.
                    end
                end
                send_data_lsb_state: begin
                    if(bitcount_lsb_data == 4'd8) begin
                        bitcount_lsb_data <= 4'd0;
                        state_reg <= wait_data_lsb_ack_state;
                    end
                    else begin
                        shift_reg_lsb_data <= {shift_reg_lsb_data[6:0], 1'b0};
                        bitcount_lsb_data <= bitcount_lsb_data + 4'd1;
                        state_reg <= send_data_lsb_state;
                    end
                end
                wait_data_lsb_ack_state: begin
                    if(sda == 1'b0) begin
                        done <= 1'b1;   //transaction is done
                        state_reg <= stop_state;
                    end
                    else begin
                        nACK <= 1'b1;   //no ack from the device
                        state_reg <= stop_state;    //we transit to stop state when there is not lsb data ack from the device.
                    end
                end
                stop_state: begin
                    if(scl == 1'b1) begin
                        sda_dir <= 1'b1;    //sda line is driven by master
                        sda_out <= 1'b1;
                        bus_busy <= 1'b0;
                        state_reg <= idle_state;
                    end
                    else begin
                        state_reg <= stop_state;
                    end
                end
                default: state_reg <= idle_state;
            endcase
        end
    end

assign sda = sda_dir ? sda_out : 1'bz;  //sda is high impedance when sda_dir is 0

endmodule

Vivado/i2c_controller_mcp4725/i2c_controller_mcp4725.srcs/sources_1/new/i2c_controller_mcp4725_tb.v
`include "i2c_controller_mcp4725.v"
`timescale 1ns / 1ps 

module i2c_controller_mcp4725_tb();
	reg clk;					// FPGA clock
    reg reset;				// Reset line
    //reg  [15:0] data,		    // 16-bit data byte
    wire scl;             // I2C clock line
    inout wire sda;              // I2C data line
    wire done;             // Done signal to indicate end of transaction
    wire nACK;             // NACK signal to indicate no ack from the device
    wire bus_busy;                   // signal to report bus busy

	
	//Instantitae the UUT
	i2c_controller_mcp4725 uut0(
		.clk(clk),
		.reset(reset),
		//.control(control),
		//.data(data),
		.scl(scl),
		.sda(sda),
		.done(done),
		.nACK(nACK),
		.bus_busy(bus_busy)
	);
	
	initial begin
		clk = 1;
		reset = 1;
		//control = 8'hFF;
		//data = 8'hAB;
		//start = 1;
	end
	
	always #50 clk = !clk;	//100MHz FPGA clock
	
	initial begin
		#200 	reset = 1'b0;
		//#200		start = 1'b0;
		//#200		start = 1'b1;
		#10000000	$finish;
	end
	
	initial begin
		$dumpfile("i2c_controller_mcp4725.vcd");
		$dumpvars;
	end
	
	/*
	initial begin
		$display("\t, \ttime, \tclk, \treset, \tstart, \tmosi, \tdone");
		$monitor("%d, \t%d, \t%d, \t%d, \%d, \%d", $time, clk, reset, start, mosi, done);
	end
	*/
endmodule

Vivado/i2c_controller_mcp4725/i2c_controller_mcp4725.srcs/sources_1/new/i2c_controller_mcp4725.vcd
$date
	Mon Jan 13 12:04:49 2025
$end
$version
	Icarus Verilog
$end
$timescale
	1ps
$end
$scope module i2c_controller_mcp4725_tb $end
$var wire 1 ! sda $end
$var wire 1 " scl $end
$var wire 1 # nACK $end
$var wire 1 $ done $end
$var wire 1 % bus_busy $end
$var reg 1 & clk $end
$var reg 1 ' reset $end
$scope module uut0 $end
$var wire 1 & clk $end
$var wire 1 ' reset $end
$var wire 1 ! sda $end
$var parameter 16 ( CLKDIV $end
$var parameter 8 ) CMDBYTE $end
$var parameter 8 * LSBBYTE $end
$var parameter 7 + MCP4725 $end
$var parameter 8 , MSBBYTE $end
$var parameter 8 - SCL_SETUP_DLY $end
$var parameter 4 . bus_idle_state $end
$var parameter 4 / idle_state $end
$var parameter 4 0 send_addr_state $end
$var parameter 4 1 send_cmd_state $end
$var parameter 4 2 send_data_lsb_state $end
$var parameter 4 3 send_data_msb_state $end
$var parameter 4 4 start_state $end
$var parameter 4 5 stop_state $end
$var parameter 4 6 wait_ack_addr_state $end
$var parameter 4 7 wait_cmd_ack_state $end
$var parameter 4 8 wait_data_lsb_ack_state $end
$var parameter 4 9 wait_data_msb_ack_state $end
$var reg 4 : bitcount_addr [3:0] $end
$var reg 4 ; bitcount_cmd [3:0] $end
$var reg 4 < bitcount_lsb_data [3:0] $end
$var reg 4 = bitcount_msb_data [3:0] $end
$var reg 1 % bus_busy $end
$var reg 8 > bus_idle_counter [7:0] $end
$var reg 16 ? clk_div_counter [15:0] $end
$var reg 1 $ done $end
$var reg 1 # nACK $end
$var reg 1 " scl $end
$var reg 1 @ sda_dir $end
$var reg 1 A sda_out $end
$var reg 8 B shift_reg_addr [7:0] $end
$var reg 8 C shift_reg_cmd [7:0] $end
$var reg 8 D shift_reg_lsb_data [7:0] $end
$var reg 8 E shift_reg_msb_data [7:0] $end
$var reg 4 F state_reg [3:0] $end
$upscope $end
$upscope $end
$enddefinitions $end
$comment Show the parameter values. $end
$dumpall
b1000 9
b1010 8
b110 7
b100 6
b1011 5
b10 4
b111 3
b1001 2
b101 1
b11 0
b0 /
b1 .
b1100100 -
b1010 ,
b1100000 +
b10111100 *
b1011001 )
b111110100 (
$end
#0
$dumpvars
b0 F
bx E
bx D
bx C
bx B
1A
0@
b0 ?
bx >
bx =
bx <
bx ;
bx :
1'
1&
x%
x$
x#
1"
z!
$end
#50000
0&
#100000
1&
#150000
0&
#200000
b1 ?
1&
0'
#250000
zA
0&
#300000
b10 ?
1&
#350000
0&
#400000
b11 ?
1&
#450000
0&
#500000
b100 ?
1&
#550000
0&
#600000
b101 ?
1&
#650000
0&
#700000
b110 ?
1&
#750000
0&
#800000
b111 ?
1&
#850000
0&
#900000
b1000 ?
1&
#950000
0&
#1000000
b1001 ?
1&
#1050000
0&
#1100000
b1010 ?
1&
#1150000
0&
#1200000
b1011 ?
1&
#1250000
0&
#1300000
b1100 ?
1&
#1350000
0&
#1400000
b1101 ?
1&
#1450000
0&
#1500000
b1110 ?
1&
#1550000
0&
#1600000
b1111 ?
1&
#1650000
0&
#1700000
b10000 ?
1&
#1750000
0&
#1800000
b10001 ?
1&
#1850000
0&
#1900000
b10010 ?
1&
#1950000
0&
#2000000
b10011 ?
1&
#2050000
0&
#2100000
b10100 ?
1&
#2150000
0&
#2200000
b10101 ?
1&
#2250000
0&
#2300000
b10110 ?
1&
#2350000
0&
#2400000
b10111 ?
1&
#2450000
0&
#2500000
b11000 ?
1&
#2550000
0&
#2600000
b11001 ?
1&
#2650000
0&
#2700000
b11010 ?
1&
#2750000
0&
#2800000
b11011 ?
1&
#2850000
0&
#2900000
b11100 ?
1&
#2950000
0&
#3000000
b11101 ?
1&
#3050000
0&
#3100000
b11110 ?
1&
#3150000
0&
#3200000
b11111 ?
1&
#3250000
0&
#3300000
b100000 ?
1&
#3350000
0&
#3400000
b100001 ?
1&
#3450000
0&
#3500000
b100010 ?
1&
#3550000
0&
#3600000
b100011 ?
1&
#3650000
0&
#3700000
b100100 ?
1&
#3750000
0&
#3800000
b100101 ?
1&
#3850000
0&
#3900000
b100110 ?
1&
#3950000
0&
#4000000
b100111 ?
1&
#4050000
0&
#4100000
b101000 ?
1&
#4150000
0&
#4200000
b101001 ?
1&
#4250000
0&
#4300000
b101010 ?
1&
#4350000
0&
#4400000
b101011 ?
1&
#4450000
0&
#4500000
b101100 ?
1&
#4550000
0&
#4600000
b101101 ?
1&
#4650000
0&
#4700000
b101110 ?
1&
#4750000
0&
#4800000
b101111 ?
1&
#4850000
0&
#4900000
b110000 ?
1&
#4950000
0&
#5000000
b110001 ?
1&
#5050000
0&
#5100000
b110010 ?
1&
#5150000
0&
#5200000
b110011 ?
1&
#5250000
0&
#5300000
b110100 ?
1&
#5350000
0&
#5400000
b110101 ?
1&
#5450000
0&
#5500000
b110110 ?
1&
#5550000
0&
#5600000
b110111 ?
1&
#5650000
0&
#5700000
b111000 ?
1&
#5750000
0&
#5800000
b111001 ?
1&
#5850000
0&
#5900000
b111010 ?
1&
#5950000
0&
#6000000
b111011 ?
1&
#6050000
0&
#6100000
b111100 ?
1&
#6150000
0&
#6200000
b111101 ?
1&
#6250000
0&
#6300000
b111110 ?
1&
#6350000
0&
#6400000
b111111 ?
1&
#6450000
0&
#6500000
b1000000 ?
1&
#6550000
0&
#6600000
b1000001 ?
1&
#6650000
0&
#6700000
b1000010 ?
1&
#6750000
0&
#6800000
b1000011 ?
1&
#6850000
0&
#6900000
b1000100 ?
1&
#6950000
0&
#7000000
b1000101 ?
1&
#7050000
0&
#7100000
b1000110 ?
1&
#7150000
0&
#7200000
b1000111 ?
1&
#7250000
0&
#7300000
b1001000 ?
1&
#7350000
0&
#7400000
b1001001 ?
1&
#7450000
0&
#7500000
b1001010 ?
1&
#7550000
0&
#7600000
b1001011 ?
1&
#7650000
0&
#7700000
b1001100 ?
1&
#7750000
0&
#7800000
b1001101 ?
1&
#7850000
0&
#7900000
b1001110 ?
1&
#7950000
0&
#8000000
b1001111 ?
1&
#8050000
0&
#8100000
b1010000 ?
1&
#8150000
0&
#8200000
b1010001 ?
1&
#8250000
0&
#8300000
b1010010 ?
1&
#8350000
0&
#8400000
b1010011 ?
1&
#8450000
0&
#8500000
b1010100 ?
1&
#8550000
0&
#8600000
b1010101 ?
1&
#8650000
0&
#8700000
b1010110 ?
1&
#8750000
0&
#8800000
b1010111 ?
1&
#8850000
0&
#8900000
b1011000 ?
1&
#8950000
0&
#9000000
b1011001 ?
1&
#9050000
0&
#9100000
b1011010 ?
1&
#9150000
0&
#9200000
b1011011 ?
1&
#9250000
0&
#9300000
b1011100 ?
1&
#9350000
0&
#9400000
b1011101 ?
1&
#9450000
0&
#9500000
b1011110 ?
1&
#9550000
0&
#9600000
b1011111 ?
1&
#9650000
0&
#9700000
b1100000 ?
1&
#9750000
0&
#9800000
b1100001 ?
1&
#9850000
0&
#9900000
b1100010 ?
1&
#9950000
0&
#10000000
b1100011 ?
1&
#10050000
0&
#10100000
b1100100 ?
1&
#10150000
0&
#10200000
b1100101 ?
b1 F
0%
0$
0#
b1010 E
b10111100 D
b1011001 C
b11000000 B
b0 :
b0 >
1&
#10250000
0&
#10300000
b1100110 ?
1&
#10350000
0&
#10400000
b1100111 ?
1&
#10450000
0&
#10500000
b1101000 ?
1&
#10550000
0&
#10600000
b1101001 ?
1&
#10650000
0&
#10700000
b1101010 ?
1&
#10750000
0&
#10800000
b1101011 ?
1&
#10850000
0&
#10900000
b1101100 ?
1&
#10950000
0&
#11000000
b1101101 ?
1&
#11050000
0&
#11100000
b1101110 ?
1&
#11150000
0&
#11200000
b1101111 ?
1&
#11250000
0&
#11300000
b1110000 ?
1&
#11350000
0&
#11400000
b1110001 ?
1&
#11450000
0&
#11500000
b1110010 ?
1&
#11550000
0&
#11600000
b1110011 ?
1&
#11650000
0&
#11700000
b1110100 ?
1&
#11750000
0&
#11800000
b1110101 ?
1&
#11850000
0&
#11900000
b1110110 ?
1&
#11950000
0&
#12000000
b1110111 ?
1&
#12050000
0&
#12100000
b1111000 ?
1&
#12150000
0&
#12200000
b1111001 ?
1&
#12250000
0&
#12300000
b1111010 ?
1&
#12350000
0&
#12400000
b1111011 ?
1&
#12450000
0&
#12500000
b1111100 ?
1&
#12550000
0&
#12600000
b1111101 ?
1&
#12650000
0&
#12700000
b1111110 ?
1&
#12750000
0&
#12800000
b1111111 ?
1&
#12850000
0&
#12900000
b10000000 ?
1&
#12950000
0&
#13000000
b10000001 ?
1&
#13050000
0&
#13100000
b10000010 ?
1&
#13150000
0&
#13200000
b10000011 ?
1&
#13250000
0&
#13300000
b10000100 ?
1&
#13350000
0&
#13400000
b10000101 ?
1&
#13450000
0&
#13500000
b10000110 ?
1&
#13550000
0&
#13600000
b10000111 ?
1&
#13650000
0&
#13700000
b10001000 ?
1&
#13750000
0&
#13800000
b10001001 ?
1&
#13850000
0&
#13900000
b10001010 ?
1&
#13950000
0&
#14000000
b10001011 ?
1&
#14050000
0&
#14100000
b10001100 ?
1&
#14150000
0&
#14200000
b10001101 ?
1&
#14250000
0&
#14300000
b10001110 ?
1&
#14350000
0&
#14400000
b10001111 ?
1&
#14450000
0&
#14500000
b10010000 ?
1&
#14550000
0&
#14600000
b10010001 ?
1&
#14650000
0&
#14700000
b10010010 ?
1&
#14750000
0&
#14800000
b10010011 ?
1&
#14850000
0&
#14900000
b10010100 ?
1&
#14950000
0&
#15000000
b10010101 ?
1&
#15050000
0&
#15100000
b10010110 ?
1&
#15150000
0&
#15200000
b10010111 ?
1&
#15250000
0&
#15300000
b10011000 ?
1&
#15350000
0&
#15400000
b10011001 ?
1&
#15450000
0&
#15500000
b10011010 ?
1&
#15550000
0&
#15600000
b10011011 ?
1&
#15650000
0&
#15700000
b10011100 ?
1&
#15750000
0&
#15800000
b10011101 ?
1&
#15850000
0&
#15900000
b10011110 ?
1&
#15950000
0&
#16000000
b10011111 ?
1&
#16050000
0&
#16100000
b10100000 ?
1&
#16150000
0&
#16200000
b10100001 ?
1&
#16250000
0&
#16300000
b10100010 ?
1&
#16350000
0&
#16400000
b10100011 ?
1&
#16450000
0&
#16500000
b10100100 ?
1&
#16550000
0&
#16600000
b10100101 ?
1&
#16650000
0&
#16700000
b10100110 ?
1&
#16750000
0&
#16800000
b10100111 ?
1&
#16850000
0&
#16900000
b10101000 ?
1&
#16950000
0&
#17000000
b10101001 ?
1&
#17050000
0&
#17100000
b10101010 ?
1&
#17150000
0&
#17200000
b10101011 ?
1&
#17250000
0&
#17300000
b10101100 ?
1&
#17350000
0&
#17400000
b10101101 ?
1&
#17450000
0&
#17500000
b10101110 ?
1&
#17550000
0&
#17600000
b10101111 ?
1&
#17650000
0&
#17700000
b10110000 ?
1&
#17750000
0&
#17800000
b10110001 ?
1&
#17850000
0&
#17900000
b10110010 ?
1&
#17950000
0&
#18000000
b10110011 ?
1&
#18050000
0&
#18100000
b10110100 ?
1&
#18150000
0&
#18200000
b10110101 ?
1&
#18250000
0&
#18300000
b10110110 ?
1&
#18350000
0&
#18400000
b10110111 ?
1&
#18450000
0&
#18500000
b10111000 ?
1&
#18550000
0&
#18600000
b10111001 ?
1&
#18650000
0&
#18700000
b10111010 ?
1&
#18750000
0&
#18800000
b10111011 ?
1&
#18850000
0&
#18900000
b10111100 ?
1&
#18950000
0&
#19000000
b10111101 ?
1&
#19050000
0&
#19100000
b10111110 ?
1&
#19150000
0&
#19200000
b10111111 ?
1&
#19250000
0&
#19300000
b11000000 ?
1&
#19350000
0&
#19400000
b11000001 ?
1&
#19450000
0&
#19500000
b11000010 ?
1&
#19550000
0&
#19600000
b11000011 ?
1&
#19650000
0&
#19700000
b11000100 ?
1&
#19750000
0&
#19800000
b11000101 ?
1&
#19850000
0&
#19900000
b11000110 ?
1&
#19950000
0&
#20000000
b11000111 ?
1&
#20050000
0&
#20100000
b11001000 ?
1&
#20150000
0&
#20200000
b11001001 ?
1&
#20250000
0&
#20300000
b11001010 ?
1&
#20350000
0&
#20400000
b11001011 ?
1&
#20450000
0&
#20500000
b11001100 ?
1&
#20550000
0&
#20600000
b11001101 ?
1&
#20650000
0&
#20700000
b11001110 ?
1&
#20750000
0&
#20800000
b11001111 ?
1&
#20850000
0&
#20900000
b11010000 ?
1&
#20950000
0&
#21000000
b11010001 ?
1&
#21050000
0&
#21100000
b11010010 ?
1&
#21150000
0&
#21200000
b11010011 ?
1&
#21250000
0&
#21300000
b11010100 ?
1&
#21350000
0&
#21400000
b11010101 ?
1&
#21450000
0&
#21500000
b11010110 ?
1&
#21550000
0&
#21600000
b11010111 ?
1&
#21650000
0&
#21700000
b11011000 ?
1&
#21750000
0&
#21800000
b11011001 ?
1&
#21850000
0&
#21900000
b11011010 ?
1&
#21950000
0&
#22000000
b11011011 ?
1&
#22050000
0&
#22100000
b11011100 ?
1&
#22150000
0&
#22200000
b11011101 ?
1&
#22250000
0&
#22300000
b11011110 ?
1&
#22350000
0&
#22400000
b11011111 ?
1&
#22450000
0&
#22500000
b11100000 ?
1&
#22550000
0&
#22600000
b11100001 ?
1&
#22650000
0&
#22700000
b11100010 ?
1&
#22750000
0&
#22800000
b11100011 ?
1&
#22850000
0&
#22900000
b11100100 ?
1&
#22950000
0&
#23000000
b11100101 ?
1&
#23050000
0&
#23100000
b11100110 ?
1&
#23150000
0&
#23200000
b11100111 ?
1&
#23250000
0&
#23300000
b11101000 ?
1&
#23350000
0&
#23400000
b11101001 ?
1&
#23450000
0&
#23500000
b11101010 ?
1&
#23550000
0&
#23600000
b11101011 ?
1&
#23650000
0&
#23700000
b11101100 ?
1&
#23750000
0&
#23800000
b11101101 ?
1&
#23850000
0&
#23900000
b11101110 ?
1&
#23950000
0&
#24000000
b11101111 ?
1&
#24050000
0&
#24100000
b11110000 ?
1&
#24150000
0&
#24200000
b11110001 ?
1&
#24250000
0&
#24300000
b11110010 ?
1&
#24350000
0&
#24400000
b11110011 ?
1&
#24450000
0&
#24500000
b11110100 ?
1&
#24550000
0&
#24600000
b11110101 ?
1&
#24650000
0&
#24700000
b11110110 ?
1&
#24750000
0&
#24800000
b11110111 ?
1&
#24850000
0&
#24900000
b11111000 ?
1&
#24950000
0&
#25000000
b11111001 ?
1&
#25050000
0&
#25100000
b11111010 ?
1&
#25150000
0&
#25200000
b11111011 ?
1&
#25250000
0&
#25300000
b11111100 ?
1&
#25350000
0&
#25400000
b11111101 ?
1&
#25450000
0&
#25500000
b11111110 ?
1&
#25550000
0&
#25600000
b11111111 ?
1&
#25650000
0&
#25700000
b100000000 ?
1&
#25750000
0&
#25800000
b100000001 ?
1&
#25850000
0&
#25900000
b100000010 ?
1&
#25950000
0&
#26000000
b100000011 ?
1&
#26050000
0&
#26100000
b100000100 ?
1&
#26150000
0&
#26200000
b100000101 ?
1&
#26250000
0&
#26300000
b100000110 ?
1&
#26350000
0&
#26400000
b100000111 ?
1&
#26450000
0&
#26500000
b100001000 ?
1&
#26550000
0&
#26600000
b100001001 ?
1&
#26650000
0&
#26700000
b100001010 ?
1&
#26750000
0&
#26800000
b100001011 ?
1&
#26850000
0&
#26900000
b100001100 ?
1&
#26950000
0&
#27000000
b100001101 ?
1&
#27050000
0&
#27100000
b100001110 ?
1&
#27150000
0&
#27200000
b100001111 ?
1&
#27250000
0&
#27300000
b100010000 ?
1&
#27350000
0&
#27400000
b100010001 ?
1&
#27450000
0&
#27500000
b100010010 ?
1&
#27550000
0&
#27600000
b100010011 ?
1&
#27650000
0&
#27700000
b100010100 ?
1&
#27750000
0&
#27800000
b100010101 ?
1&
#27850000
0&
#27900000
b100010110 ?
1&
#27950000
0&
#28000000
b100010111 ?
1&
#28050000
0&
#28100000
b100011000 ?
1&
#28150000
0&
#28200000
b100011001 ?
1&
#28250000
0&
#28300000
b100011010 ?
1&
#28350000
0&
#28400000
b100011011 ?
1&
#28450000
0&
#28500000
b100011100 ?
1&
#28550000
0&
#28600000
b100011101 ?
1&
#28650000
0&
#28700000
b100011110 ?
1&
#28750000
0&
#28800000
b100011111 ?
1&
#28850000
0&
#28900000
b100100000 ?
1&
#28950000
0&
#29000000
b100100001 ?
1&
#29050000
0&
#29100000
b100100010 ?
1&
#29150000
0&
#29200000
b100100011 ?
1&
#29250000
0&
#29300000
b100100100 ?
1&
#29350000
0&
#29400000
b100100101 ?
1&
#29450000
0&
#29500000
b100100110 ?
1&
#29550000
0&
#29600000
b100100111 ?
1&
#29650000
0&
#29700000
b100101000 ?
1&
#29750000
0&
#29800000
b100101001 ?
1&
#29850000
0&
#29900000
b100101010 ?
1&
#29950000
0&
#30000000
b100101011 ?
1&
#30050000
0&
#30100000
b100101100 ?
1&
#30150000
0&
#30200000
b100101101 ?
1&
#30250000
0&
#30300000
b100101110 ?
1&
#30350000
0&
#30400000
b100101111 ?
1&
#30450000
0&
#30500000
b100110000 ?
1&
#30550000
0&
#30600000
b100110001 ?
1&
#30650000
0&
#30700000
b100110010 ?
1&
#30750000
0&
#30800000
b100110011 ?
1&
#30850000
0&
#30900000
b100110100 ?
1&
#30950000
0&
#31000000
b100110101 ?
1&
#31050000
0&
#31100000
b100110110 ?
1&
#31150000
0&
#31200000
b100110111 ?
1&
#31250000
0&
#31300000
b100111000 ?
1&
#31350000
0&
#31400000
b100111001 ?
1&
#31450000
0&
#31500000
b100111010 ?
1&
#31550000
0&
#31600000
b100111011 ?
1&
#31650000
0&
#31700000
b100111100 ?
1&
#31750000
0&
#31800000
b100111101 ?
1&
#31850000
0&
#31900000
b100111110 ?
1&
#31950000
0&
#32000000
b100111111 ?
1&
#32050000
0&
#32100000
b101000000 ?
1&
#32150000
0&
#32200000
b101000001 ?
1&
#32250000
0&
#32300000
b101000010 ?
1&
#32350000
0&
#32400000
b101000011 ?
1&
#32450000
0&
#32500000
b101000100 ?
1&
#32550000
0&
#32600000
b101000101 ?
1&
#32650000
0&
#32700000
b101000110 ?
1&
#32750000
0&
