shiftreg8/my_dff8.v
module my_dff8(
    input clk,
    input [7:0] d,
    output reg [7:0] q
);

always @(posedge clk) begin
    q <= d;
end
    
endmodule

shiftreg8/shiftreg8_3.v
//`include "my_dff8.v"

module shiftreg8_3 (
    input clk,
    input [7:0] d,
    input [1:0] sel,
    output reg [7:0] q
);

wire [7:0] q1, q2, q3;

//instantiate my_dff8 for 3 times
my_dff8 my_dff8_1(
    .clk(clk),
    .d(d),
    .q(q1)
);

my_dff8 my_dff8_2(
    .clk(clk),
    .d(q1),
    .q(q2)
);

my_dff8 my_dff8_3(
    .clk(clk),
    .d(q2),
    .q(q3)
);

always @(*) begin
    case (sel)
    2'b00    : q = d;
    2'b01    : q = q1;
    2'b10    : q = q2;
    2'b11    : q = q3;
        default: q=8'b0; 
    endcase
end
    
endmodule

shiftreg8/tb_shiftreg8_3.v
`timescale 1ns/1ps
`include "my_dff8.v"
`include "shiftreg8_3.v"

module tb_shiftreg8_3;
reg clk;
reg [7:0] d;
reg [1:0] sel;
wire [7:0] q;

//Instantiate
shiftreg8_3 uut(
    .clk(clk),
    .d(d),
    .sel(sel),
    .q(q)
);
//Initialize
initial begin
    $dumpfile("tb_shiftreg8_3.vcd");
    $dumpvars(0, tb_shiftreg8_3);
    //init inputs
    #5 clk = 0;
    d=0;
    sel=0;
    #3000 $finish;
end

always #50      clk = ~clk;
always #100      d = d + 1;
always #500     sel = sel + 1;

endmodule

shiftreg8/tb_shiftreg8_3.vcd
$date
	Thu Jun 02 10:52:10 2022
$end
$version
	Icarus Verilog
$end
$timescale
	1ps
$end
$scope module tb_shiftreg8_3 $end
$var wire 8 ! q [7:0] $end
$var reg 1 " clk $end
$var reg 8 # d [7:0] $end
$var reg 2 $ sel [1:0] $end
$scope module uut $end
$var wire 1 " clk $end
$var wire 8 % d [7:0] $end
$var wire 2 & sel [1:0] $end
$var wire 8 ' q3 [7:0] $end
$var wire 8 ( q2 [7:0] $end
$var wire 8 ) q1 [7:0] $end
$var reg 8 * q [7:0] $end
$scope module my_dff8_1 $end
$var wire 1 " clk $end
$var wire 8 + d [7:0] $end
$var reg 8 , q [7:0] $end
$upscope $end
$scope module my_dff8_2 $end
$var wire 1 " clk $end
$var wire 8 - d [7:0] $end
$var reg 8 . q [7:0] $end
$upscope $end
$scope module my_dff8_3 $end
$var wire 1 " clk $end
$var wire 8 / d [7:0] $end
$var reg 8 0 q [7:0] $end
$upscope $end
$upscope $end
$upscope $end
$enddefinitions $end
#0
$dumpvars
bx 0
bx /
bx .
bx -
bx ,
bx +
bx *
bx )
bx (
bx '
bx &
bx %
bx $
bx #
x"
bx !
$end
#5000
b0 !
b0 *
b0 $
b0 &
b0 #
b0 %
b0 +
0"
#50000
b0 )
b0 ,
b0 -
1"
#100000
b1 !
b1 *
0"
b1 #
b1 %
b1 +
#150000
b0 (
b0 .
b0 /
b1 )
b1 ,
b1 -
1"
#200000
b10 !
b10 *
0"
b10 #
b10 %
b10 +
#250000
b10 )
b10 ,
b10 -
b1 (
b1 .
b1 /
b0 '
b0 0
1"
#300000
b11 !
b11 *
0"
b11 #
b11 %
b11 +
#350000
b1 '
b1 0
b10 (
b10 .
b10 /
b11 )
b11 ,
b11 -
1"
#400000
b100 !
b100 *
0"
b100 #
b100 %
b100 +
#450000
b100 )
b100 ,
b100 -
b11 (
b11 .
b11 /
b10 '
b10 0
1"
#500000
0"
b101 #
b101 %
b101 +
b1 $
b1 &
#550000
b101 !
b101 *
b11 '
b11 0
b100 (
b100 .
b100 /
b101 )
b101 ,
b101 -
1"
#600000
0"
b110 #
b110 %
b110 +
#650000
b110 !
b110 *
b110 )
b110 ,
b110 -
b101 (
b101 .
b101 /
b100 '
b100 0
1"
#700000
0"
b111 #
b111 %
b111 +
#750000
b111 !
b111 *
b101 '
b101 0
b110 (
b110 .
b110 /
b111 )
b111 ,
b111 -
1"
#800000
0"
b1000 #
b1000 %
b1000 +
#850000
b1000 !
b1000 *
b1000 )
b1000 ,
b1000 -
b111 (
b111 .
b111 /
b110 '
b110 0
1"
#900000
0"
b1001 #
b1001 %
b1001 +
#950000
b1001 !
b1001 *
b111 '
b111 0
b1000 (
b1000 .
b1000 /
b1001 )
b1001 ,
b1001 -
1"
#1000000
b1000 !
b1000 *
0"
b1010 #
b1010 %
b1010 +
b10 $
b10 &
#1050000
b1001 !
b1001 *
b1010 )
b1010 ,
b1010 -
b1001 (
b1001 .
b1001 /
b1000 '
b1000 0
1"
#1100000
0"
b1011 #
b1011 %
b1011 +
#1150000
b1010 !
b1010 *
b1001 '
b1001 0
b1010 (
b1010 .
b1010 /
b1011 )
b1011 ,
b1011 -
1"
#1200000
0"
b1100 #
b1100 %
b1100 +
#1250000
b1011 !
b1011 *
b1100 )
b1100 ,
b1100 -
b1011 (
b1011 .
b1011 /
b1010 '
b1010 0
1"
#1300000
0"
b1101 #
b1101 %
b1101 +
#1350000
b1100 !
b1100 *
b1011 '
b1011 0
b1100 (
b1100 .
b1100 /
b1101 )
b1101 ,
b1101 -
1"
#1400000
0"
b1110 #
b1110 %
b1110 +
#1450000
b1101 !
b1101 *
b1110 )
b1110 ,
b1110 -
b1101 (
b1101 .
b1101 /
b1100 '
b1100 0
1"
#1500000
b1100 !
b1100 *
0"
b1111 #
b1111 %
b1111 +
b11 $
b11 &
#1550000
b1101 !
b1101 *
b1101 '
b1101 0
b1110 (
b1110 .
b1110 /
b1111 )
b1111 ,
b1111 -
1"
#1600000
0"
b10000 #
b10000 %
b10000 +
#1650000
b1110 !
b1110 *
b10000 )
b10000 ,
b10000 -
b1111 (
b1111 .
b1111 /
b1110 '
b1110 0
1"
#1700000
0"
b10001 #
b10001 %
b10001 +
#1750000
b1111 !
b1111 *
b1111 '
b1111 0
b10000 (
b10000 .
b10000 /
b10001 )
b10001 ,
b10001 -
1"
#1800000
0"
b10010 #
b10010 %
b10010 +
#1850000
b10000 !
b10000 *
b10010 )
b10010 ,
b10010 -
b10001 (
b10001 .
b10001 /
b10000 '
b10000 0
1"
#1900000
0"
b10011 #
b10011 %
b10011 +
#1950000
b10001 !
b10001 *
b10001 '
b10001 0
b10010 (
b10010 .
b10010 /
b10011 )
b10011 ,
b10011 -
1"
#2000000
b10100 !
b10100 *
0"
b10100 #
b10100 %
b10100 +
b0 $
b0 &
#2050000
b10100 )
b10100 ,
b10100 -
b10011 (
b10011 .
b10011 /
b10010 '
b10010 0
1"
#2100000
b10101 !
b10101 *
0"
b10101 #
b10101 %
b10101 +
#2150000
b10011 '
b10011 0
b10100 (
b10100 .
b10100 /
b10101 )
b10101 ,
b10101 -
1"
#2200000
b10110 !
b10110 *
0"
b10110 #
b10110 %
b10110 +
#2250000
b10110 )
b10110 ,
b10110 -
b10101 (
b10101 .
b10101 /
b10100 '
b10100 0
1"
#2300000
b10111 !
b10111 *
0"
b10111 #
b10111 %
b10111 +
#2350000
b10101 '
b10101 0
b10110 (
b10110 .
b10110 /
b10111 )
b10111 ,
b10111 -
1"
#2400000
b11000 !
b11000 *
0"
b11000 #
b11000 %
b11000 +
#2450000
b11000 )
b11000 ,
b11000 -
b10111 (
b10111 .
b10111 /
b10110 '
b10110 0
1"
#2500000
0"
b11001 #
b11001 %
b11001 +
b1 $
b1 &
#2550000
b11001 !
b11001 *
b10111 '
b10111 0
b11000 (
b11000 .
b11000 /
b11001 )
b11001 ,
b11001 -
1"
#2600000
0"
b11010 #
b11010 %
b11010 +
#2650000
b11010 !
b11010 *
b11010 )
b11010 ,
b11010 -
b11001 (
b11001 .
b11001 /
b11000 '
b11000 0
1"
#2700000
0"
b11011 #
b11011 %
b11011 +
#2750000
b11011 !
b11011 *
b11001 '
b11001 0
b11010 (
b11010 .
b11010 /
b11011 )
b11011 ,
b11011 -
1"
#2800000
0"
b11100 #
b11100 %
b11100 +
#2850000
b11100 !
b11100 *
b11100 )
b11100 ,
b11100 -
b11011 (
b11011 .
b11011 /
b11010 '
b11010 0
1"
#2900000
0"
b11101 #
b11101 %
b11101 +
#2950000
b11101 !
b11101 *
b11011 '
b11011 0
b11100 (
b11100 .
b11100 /
b11101 )
b11101 ,
b11101 -
1"
#3000000
b11100 !
b11100 *
0"
b11110 #
b11110 %
b11110 +
b10 $
b10 &
