fsm_mealy_2scomp/fsm_mealy_twoscomp.v
module fsm_mealy_twoscomp(
    input clk_in,
    input rst_in,
    input A_in,
    output reg N_out
);

// State encoding
parameter C0 = 1'b0,
        C1 = 1'b1;

// State variables
reg nextState, state;

// State register
always @(posedge clk_in, posedge rst_in) begin
    if(rst_in)
        state <= C1;
    else
        state <= nextState;
end

// Next state logic
always @ (*) begin
case(state)
    C1:     begin
                if(~A_in | 1'b1) 
                    nextState = C0;
                else
                    nextState = C1;    
            end
    C0:     nextState = C0;
    default:    nextState = C1;
endcase
end

// Output logic
always @(*) begin
    N_out = ((~A_in & ~state) | (A_in & state))? 1'b1: 1'b0;
end
endmodule       //end of module fsm_mealy_twoscomp

fsm_mealy_2scomp/tb_fsm_mealy_twoscomp.v
`timescale 1ns / 1ps
`include "fsm_mealy_twoscomp.v"

module tb_fsm_mealy_twoscomp;
reg clk_in, rst_in, A_in;
wire N_out;

fsm_mealy_twoscomp uut(
    .clk_in(clk_in),
    .rst_in(rst_in),
    .A_in(A_in),
    .N_out(N_out)
);

initial begin
    //dump simulation result to vcd file
    $dumpfile("tb_fsm_mealy_twoscomp.vcd");
    $dumpvars(0, tb_fsm_mealy_twoscomp);
    //init inputs
    clk_in = 0;
    rst_in = 0;
    A_in = 0;
    #1000 $finish;   //end of simulation time
end

always #50    clk_in = ~clk_in;
always #700   rst_in = ~rst_in;
always #100    A_in = ~A_in;
endmodule       //end of testbench module for fsm_mealy_2scomp

fsm_mealy_2scomp/tb_fsm_mealy_twoscomp.vcd
$date
	Sat Apr 01 08:49:53 2023
$end
$version
	Icarus Verilog
$end
$timescale
	1ps
$end
$scope module tb_fsm_mealy_twoscomp $end
$var wire 1 ! N_out $end
$var reg 1 " A_in $end
$var reg 1 # clk_in $end
$var reg 1 $ rst_in $end
$scope module uut $end
$var wire 1 " A_in $end
$var wire 1 # clk_in $end
$var wire 1 $ rst_in $end
$var reg 1 ! N_out $end
$var reg 1 % nextState $end
$var reg 1 & state $end
$upscope $end
$upscope $end
$enddefinitions $end
#0
$dumpvars
x&
1%
0$
0#
0"
x!
$end
#50000
0!
0%
1&
1#
#100000
1!
0#
1"
#150000
0!
0&
1#
#200000
1!
0#
0"
#250000
1#
#300000
0!
0#
1"
#350000
1#
#400000
1!
0#
0"
#450000
1#
#500000
0!
0#
1"
#550000
1#
#600000
1!
0#
0"
#650000
1#
#700000
1&
1!
0#
1"
1$
#750000
1#
#800000
0!
0#
0"
#850000
1#
#900000
1!
0#
1"
#950000
1#
#1000000
0!
0#
0"
